snippets/__init__.py
snippets/EulerEquation/gas1d.py
snippets/RungeKutta/ExplicitRungeKutta.py
snippets/RungeKutta/IMEXRungeKutta.py
snippets/RungeKutta/__init__.py
snippets/SlopeLimiter/SlopeLimiter.py
snippets/SlopeLimiter/__init__.py
snippets/WENO/WENO5_JS.py
snippets/WENO/WENO5_M.py
snippets/WENO/WENO5_Z.py
snippets/WENO/__init__.py
numerical_snippets-0.0.2.dist-info/LICENSE
numerical_snippets-0.0.2.dist-info/WHEEL
numerical_snippets-0.0.2.dist-info/METADATA
numerical_snippets-0.0.2.dist-info/RECORD
