Metadata-Version: 2.1
Name: numerical-snippets
Version: 0.0.2
Summary: Collection of numerical snippets in python
Author-email: Zhengyi Li <lizhengyi.pku@gmail.com>
Requires-Python: >=3.7
Requires-Dist: numpy
Requires-Dist: scipy
Project-URL: Documentation, https://numericalsnippets.readthedocs.io/en/latest
Project-URL: Homepage, https://github.com/li-positive-one/NumericalSnippets
